setup.cfg
setup.py
lognames/__init__.py
lognames/logMethod.py
lognames.egg-info/PKG-INFO
lognames.egg-info/SOURCES.txt
lognames.egg-info/dependency_links.txt
lognames.egg-info/entry_points.txt
lognames.egg-info/not-zip-safe
lognames.egg-info/top_level.txt