Metadata-Version: 1.0
Name: lognames
Version: 0.1dev
Summary: This is a package that uses logging to print the arguments and name of the method called
Home-page: http://stackoverflow.com/users/1006989/x-jacobs
Author: Xian Jacobs
Author-email: cricobs@gmail.com
License: GPL
Keywords: logging method name
Platform: UNKNOWN
